fscherf_github_actions_test_package/__init__.py
fscherf_github_actions_test_package/_version.py
fscherf_github_actions_test_package-0.1.0.dist-info/METADATA
fscherf_github_actions_test_package-0.1.0.dist-info/WHEEL
fscherf_github_actions_test_package-0.1.0.dist-info/top_level.txt
fscherf_github_actions_test_package-0.1.0.dist-info/RECORD
