Metadata-Version: 2.1
Name: fscherf-github-actions-test-package
Version: 0.1.0
Summary: fscherf github actions test package
Requires-Python: >=3.8
Provides-Extra: dev
Provides-Extra: test
